pygenieacs/__init__.py
pygenieacs/clients.py
pygenieacs/devices.py
pygenieacs/presets.py
pygenieacs/provisions.py
pygenieacs/tasks.py
pygenieacs-0.1.2.dist-info/licenses/LICENSE.txt
pygenieacs-0.1.2.dist-info/METADATA
pygenieacs-0.1.2.dist-info/WHEEL
pygenieacs-0.1.2.dist-info/top_level.txt
pygenieacs-0.1.2.dist-info/RECORD
