Metadata-Version: 2.4
Name: pygenieacs
Version: 0.1.2
Summary: Python API client for GenieACS REST API
Author-email: Uberkie <uberkie85@gmail.com>
License: MIT
Project-URL: Homepage, https://github.com/uberkie/pygenieacs
Project-URL: Repository, https://github.com/uberkie/pygenieacs
Project-URL: Issues, https://github.com/uberkie/pygenieacs/issues
Keywords: genieacs,acs,tr069,cwmp,networking
Classifier: Development Status :: 3 - Alpha
Classifier: Intended Audience :: Developers
Classifier: Programming Language :: Python :: 3
Classifier: Programming Language :: Python :: 3.9
Classifier: Programming Language :: Python :: 3.10
Classifier: Programming Language :: Python :: 3.11
Classifier: License :: OSI Approved :: MIT License
Classifier: Operating System :: OS Independent
License-File: LICENSE.txt
Requires-Dist: httpx
Dynamic: license-file
